stealth_port_scan.py
stealth_port_scan-0.0.1.dist-info/LICENSE
stealth_port_scan-0.0.1.dist-info/METADATA
stealth_port_scan-0.0.1.dist-info/WHEEL
stealth_port_scan-0.0.1.dist-info/entry_points.txt
stealth_port_scan-0.0.1.dist-info/top_level.txt
stealth_port_scan-0.0.1.dist-info/RECORD
