Metadata-Version: 2.1
Name: stealth-port-scan
Version: 0.0.1
Summary: Stealth Port Scan using TCP/SYN method
Author: Sergey M
License: You can use it as you wish as long as you credit the author.
Project-URL: Repository, https://github.com/s3rgeym/stealth-port-scan.git
Classifier: Topic :: Internet
Requires-Python: >=3.11.7
License-File: LICENSE
Provides-Extra: dev
Requires-Dist: black ; extra == 'dev'
Requires-Dist: pylint ; extra == 'dev'
Provides-Extra: test
